IMPACT/__init__.py
IMPACT/dataset/__init__.py
IMPACT/dataset/dataset.py
IMPACT/model/IMPACT.py
IMPACT/model/__init__.py
IMPACT/model/abstract_model.py
IMPACT/utils/__init__.py
IMPACT/utils/utils.py
experiments/__init__.py
experiments/datasets/__init__.py
experiments/datasets/data_utils/DeepMTP_util.py
experiments/datasets/data_utils/__init__.py
experiments/datasets/data_utils/bivae.py
experiments/datasets/data_utils/cornac_util.py
experiments/datasets/data_utils/exception.py
experiments/datasets/data_utils/preprocessing_utilities.py
experiments/datasets/data_utils/recom_bivaecf.py
experiments/datasets/data_utils/recommender.py
impact_liris-2.0.0.dist-info/LICENSE
impact_liris-2.0.0.dist-info/METADATA
impact_liris-2.0.0.dist-info/WHEEL
impact_liris-2.0.0.dist-info/top_level.txt
impact_liris-2.0.0.dist-info/RECORD
