Metadata-Version: 2.1
Name: impact-liris
Version: 2.0.0
Summary: IMPACT framework, an interpretable multi-target framework for multi-class outputs
Home-page: https://github.com/arthur-batel/IMPACT.git
Author: Arthur BATEL
Author-email: arthur.batel@insa-lyon.fr
Classifier: License :: OSI Approved :: MIT License
Classifier: Operating System :: POSIX :: Linux
Classifier: Programming Language :: Python :: 3.11
Classifier: Environment :: GPU :: NVIDIA CUDA
Requires-Python: >=3.6
License-File: LICENSE
Requires-Dist: torch
Requires-Dist: vegas
Requires-Dist: numpy
Requires-Dist: pandas
Requires-Dist: scikit-learn
Requires-Dist: scipy
Requires-Dist: tqdm
Requires-Dist: numba
Requires-Dist: tensorboardX
